pixiv_sql/__init__.py
pixiv_sql/__main__.py
pixiv_sql/lib/__init__.py
pixiv_sql/lib/logger.py
pixiv_sql/lib/pixiv.py
pixiv_sql/lib/pixivpy.py
pixiv_sql/lib/sql.py
pixiv_sql/model/__init__.py
pixiv_sql/model/base.py
pixiv_sql/model/bookmarked_illust.py
pixiv_sql/model/illust_series.py
pixiv_sql/model/illust_statistics.py
pixiv_sql/model/illust_tag.py
pixiv_sql/model/image.py
pixiv_sql/model/series.py
pixiv_sql/model/tag.py
pixiv_sql/model/type.py
pixiv_sql/model/user.py
pixiv_sql-0.9.0.dist-info/METADATA
pixiv_sql-0.9.0.dist-info/WHEEL
pixiv_sql-0.9.0.dist-info/entry_points.txt
pixiv_sql-0.9.0.dist-info/licenses/LICENSE
pixiv_sql-0.9.0.dist-info/RECORD
