Metadata-Version: 2.3
Name: pixiv-sql
Version: 0.9.0
Summary: Python library to backup pixiv user data to SQLite DB.
Project-URL: Homepage, https://github.com/ryohidaka/pixiv-sql
Project-URL: Repository, https://github.com/ryohidaka/pixiv-sql
Project-URL: Issues, https://github.com/ryohidaka/pixiv-sql/issues
Project-URL: Changelog, https://github.com/ryohidaka/blob/main/pixiv-sql/CHANGELOG.md
Author-email: ryohidaka <39184410+ryohidaka@users.noreply.github.com>
License: MIT License
License-File: LICENSE
Keywords: pixiv
Requires-Python: >=3.8
Requires-Dist: pixivpy3>=3.7.5
Requires-Dist: python-dotenv>=1.0.1
Requires-Dist: sqlalchemy>=2.0.31
Requires-Dist: tqdm>=4.66.4
